{
  "id": "crime-and-punishment-1866",
  "title": "Crime and Punishment",
  "author": "fyodor-dostoevsky",
  "year": 1866,
  "genres": [
    "Psychological fiction",
    "Philosophical novel",
    "Literary fiction"
  ],
  "pages": 671,
  "publisher": "The Russian Messenger",
  "language": "Russian",
  "country": "Russia",
  "summary": "Impoverished ex-student Raskolnikov commits murder, believing himself to be an extraordinary person above moral law, only to face psychological torment. A foundational work of psychological realism.",
  "sales": {
    "copiesSold": 10000000,
    "languages": 70,
    "source": "Wikipedia",
    "sourceUrl": "https://en.wikipedia.org/wiki/Crime_and_Punishment"
  },
  "ratings": {
    "goodreads": {
      "score": 4.24,
      "max": 5
    }
  },
  "rank": 94,
  "images": [
    {
      "url": "https://covers.openlibrary.org/b/id/14938768-L.jpg",
      "type": "cover",
      "isPrimary": true,
      "alt": "Crime and Punishment (A Bantam Classic) {Complete and Unabridged} cover",
      "attribution": {
        "source": "Open Library",
        "licence": "open-data",
        "licenceUrl": "https://openlibrary.org/developers/api",
        "note": "Book data from Open Library (openlibrary.org), part of Internet Archive.",
        "sourceUrl": "https://openlibrary.org/works/OL36435681W"
      }
    }
  ],
  "detailUrls": [
    {
      "url": "https://en.wikipedia.org/wiki/Crime_and_Punishment",
      "source": "Wikipedia"
    },
    {
      "url": "https://openlibrary.org/works/OL36435681W",
      "source": "Open Library"
    }
  ],
  "editionCount": 1,
  "_openlibrary_work_key": "/works/OL36435681W"
}
